pyscaffoldext/__init__.py
pyscaffoldext/pyproject/__init__.py
pyscaffoldext/pyproject/extension.py
pyscaffoldext/pyproject/templates/__init__.py
pyscaffoldext/pyproject/templates/pyproject_toml.template
pyscaffoldext_pyproject-0.2.1.dist-info/AUTHORS.rst
pyscaffoldext_pyproject-0.2.1.dist-info/LICENSE.txt
pyscaffoldext_pyproject-0.2.1.dist-info/METADATA
pyscaffoldext_pyproject-0.2.1.dist-info/WHEEL
pyscaffoldext_pyproject-0.2.1.dist-info/entry_points.txt
pyscaffoldext_pyproject-0.2.1.dist-info/top_level.txt
pyscaffoldext_pyproject-0.2.1.dist-info/RECORD
