Metadata-Version: 2.1
Name: pyscaffoldext-pyproject
Version: 0.2.1
Summary: PyScaffold extension adding a pyproject.toml file
Home-page: https://github.com/pyscaffold/pyscaffoldext-pyproject
Author: Florian Wilhelm
Author-email: florian.wilhelm@gmail.com
License: mit
Project-URL: Documentation, https://pyscaffold.org/
Project-URL: Twitter, https://twitter.com/PyScaffold
Platform: any
Classifier: Development Status :: 4 - Beta
Classifier: Programming Language :: Python
Classifier: Programming Language :: Python :: 3
Classifier: Programming Language :: Python :: 3 :: Only
Classifier: Programming Language :: Python :: 3.4
Classifier: Programming Language :: Python :: 3.5
Classifier: Programming Language :: Python :: 3.6
Classifier: Programming Language :: Python :: 3.7
Classifier: Environment :: Console
Classifier: Intended Audience :: Developers
Classifier: License :: OSI Approved :: MIT License
Classifier: Operating System :: POSIX :: Linux
Classifier: Operating System :: Unix
Classifier: Operating System :: MacOS
Classifier: Operating System :: Microsoft :: Windows
Requires-Dist: pyscaffold (<4.0a0,>=3.2a0)
Provides-Extra: testing
Requires-Dist: flake8 ; extra == 'testing'
Requires-Dist: pytest ; extra == 'testing'
Requires-Dist: pytest-cov ; extra == 'testing'
Requires-Dist: pytest-virtualenv ; extra == 'testing'
Requires-Dist: pytest-xdist ; extra == 'testing'
